Workbook

Sheet Summary
A1: Luca – 12-month financial model
A2: All data fictional. Inputs are on the Assumptions and Headcount tabs.
B4: Key figures | C4: Month 1 | D4: Month 12 | E4: 12-month total
B5: Revenue | C5: ='P&L'!C7 | D5: ='P&L'!N7 | E5: ='P&L'!O7
B6: Gross margin % | C6: ='P&L'!C8 | D6: ='P&L'!N8 | E6: ='P&L'!O8
B7: Total operating expenses | C7: =-'P&L'!C18 | D7: =-'P&L'!N18 | E7: =-'P&L'!O18
B8: Operating profit | C8: ='P&L'!C20 | D8: ='P&L'!N20 | E8: ='P&L'!O20
B9: Headcount (new hires, end of month) | C9: =Headcount!C14 | D9: =Headcount!N14
B10: Cash position – without loan | C10: =Runway!C9 | D10: =Runway!N9
B11: Cash position – with loan | C11: =Runway!C17 | D11: =Runway!N17
B12: Runway – without loan | E12: =Runway!C30
B13: Runway – with loan | E13: =Runway!D30
B16: Tabs
B17: Assumptions – every number from the case brief, plus opening cash (my assumption).
B18: Headcount – new senior / junior hires per month → headcount and people costs.
B19: P&L – revenue, gross margin, costs, operating profit; net profit with and without loan interest.
B20: Cash Flow – indirect method, once without the loan and once with it.
B21: Loan – 24-month repayment schedule in EUR and USD.
B22: Runway – monthly and cumulative cash position, burn and runway, with vs. without the loan.
B24: Note
B25: Runway isn't a real constraint in this case. Luca generates $0.9–1.5M of cash every month (about $13.6M
B26: over the 12 months), and I don't have the company's overall cost base: the model only includes the
B27: 25 new hires, overhead and G&A.

Sheet Assumptions
A1: Assumptions
A2: Blue cells on yellow are inputs; everything else in the workbook is a formula. All values come from the case brief except where the Source column says otherwise.
B4: Revenue | C4: Value | D4: Source
B5: Starting monthly revenue (Month 1) | C5: 1500000 | D5: Case brief.
B6: Growth, month over month (compound) | C6: 0.06 | D6: Case brief.
B7: Gross margin, Month 1 | C7: 0.65 | D7: Case brief.
B8: Gross margin, Month 12 | C8: 0.6 | D8: Case brief. Compresses in equal steps between Month 1 and Month 12 (about −0.45 points a month).
B10: Hiring | C10: Value | D10: Source
B11: Junior salary (per month) | C11: 3000 | D11: Case brief.
B12: Senior salary (per month) | C12: 6000 | D12: Case brief.
B13: Hiring cost (one-off, per hire) | C13: 6000 | D13: Case brief. Booked in the month the person starts.
B14: Benefits (% of total salary) | C14: 0.15 | D14: Case brief.
B15: The 25 hires and their start months are set on the Headcount tab.
B17: Operating expenses | C17: Value | D17: Source
B18: Overhead, Month 1 (per month) | C18: 40000 | D18: Case brief.
B19: Overhead growth over 12 months | C19: 0.15 | D19: Case brief allows linear or another approach. Chosen: linear, so it rises by the same amount each month, from $40,000 in Month 1 to $46,000 in Month 12.
B20: G&A / Legal (per month, fixed) | C20: 20000 | D20: Case brief.
B22: Cash | C22: Value | D22: Source
B23: Opening cash balance (start of Month 1) | C23: 3000000 | D23: MY ASSUMPTION (not in brief): needed to calculate cash position and runway. Change it freely.
B25: Loan scenario | C25: Value | D25: Source
B26: Loan amount (EUR) | C26: 500000 | D26: Case brief. Assumed received in full in Month 1.
B27: Interest rate (annual) | C27: 0.06 | D27: Case brief. 0.5% per month.
B28: Term (months) | C28: 24 | D28: Case brief.
B29: Interest-only months | C29: 6 | D29: Case brief. Then equal monthly payments over the remaining 18 months.
B30: FX rate (USD per EUR) | C30: 1.1 | D30: Case brief.
B32: Not modelled because the brief does not mention them:
B33: income tax, depreciation, customer payment delays (receivables), supplier payment terms and capital expenditure. Revenue is treated as collected, and costs as paid, in the month they occur.

Sheet Headcount
A1: Headcount plan & hiring costs
A2: Enter new senior and junior hires per month (blue cells). The case requires 25 hires within Months 1–6.
A4: USD | C4: 1 | D4: 2 | E4: 3 | F4: 4 | G4: 5 | H4: 6 | I4: 7 | J4: 8 | K4: 9 | L4: 10 | M4: 11 | N4: 12 | O4: 12-month total
A6: New hires (input)
A7: New senior hires | C7: 3 | D7: 2 | E7: 2 | F7: 1 | G7: 1 | H7: 1 | I7: 0 | J7: 0 | K7: 0 | L7: 0 | M7: 0 | N7: 0 | O7: =SUM(C7:N7)
A8: New junior hires | C8: 2 | D8: 3 | E8: 3 | F8: 3 | G8: 2 | H8: 2 | I8: 0 | J8: 0 | K8: 0 | L8: 0 | M8: 0 | N8: 0 | O8: =SUM(C8:N8)
A9: Total new hires | C9: =C7+C8 | D9: =D7+D8 | E9: =E7+E8 | F9: =F7+F8 | G9: =G7+G8 | H9: =H7+H8 | I9: =I7+I8 | J9: =J7+J8 | ... N9: =N7+N8 | O9: =SUM(C9:N9)
A11: Headcount at end of month
A12: Senior | C12: =SUM($C7:C7) | D12: =SUM($C7:D7) | E12: =SUM($C7:E7) | F12: =SUM($C7:F7) | G12: =SUM($C7:G7) | H12: =SUM($C7:H7) | I12: =SUM($C7:I7) | J12: =SUM($C7:J7) | ... N12: =SUM($C7:N7) | O12: =N12
A13: Junior | C13: =SUM($C8:C8) | D13: =SUM($C8:D8) | E13: =SUM($C8:E8) | F13: =SUM($C8:F8) | G13: =SUM($C8:G8) | H13: =SUM($C8:H8) | I13: =SUM($C8:I8) | J13: =SUM($C8:J8) | ... N13: =SUM($C8:N8) | O13: =N13
A14: Total headcount (new hires) | C14: =C12+C13 | D14: =D12+D13 | E14: =E12+E13 | F14: =F12+F13 | G14: =G12+G13 | H14: =H12+H13 | I14: =I12+I13 | J14: =J12+J13 | ... N14: =N12+N13 | O14: =N14
A16: People costs
A17: Salaries | C17: =C12*Assumptions!$C$12+C13*Assumptions!$C$11 | D17: =D12*Assumptions!$C$12+D13*Assumptions!$C$11 | E17: =E12*Assumptions!$C$12+E13*Assumptions!$C$11 | F17: =F12*Assumptions!$C$12+F13*Assumptions!$C$11 | G17: =G12*Assumptions!$C$12+G13*Assumptions!$C$11 | H17: =H12*Assumptions!$C$12+H13*Assumptions!$C$11 | I17: =I12*Assumptions!$C$12+I13*Assumptions!$C$11 | J17: =J12*Assumptions!$C$12+J13*Assumptions!$C$11 | ... N17: =N12*Assumptions!$C$12+N13*Assumptions!$C$11 | O17: =SUM(C17:N17)
A18: Benefits (15% of salary) | C18: =C17*Assumptions!$C$14 | D18: =D17*Assumptions!$C$14 | E18: =E17*Assumptions!$C$14 | F18: =F17*Assumptions!$C$14 | G18: =G17*Assumptions!$C$14 | H18: =H17*Assumptions!$C$14 | I18: =I17*Assumptions!$C$14 | J18: =J17*Assumptions!$C$14 | ... N18: =N17*Assumptions!$C$14 | O18: =SUM(C18:N18)
A19: Hiring costs ($6,000 per new hire) | C19: =C9*Assumptions!$C$13 | D19: =D9*Assumptions!$C$13 | E19: =E9*Assumptions!$C$13 | F19: =F9*Assumptions!$C$13 | G19: =G9*Assumptions!$C$13 | H19: =H9*Assumptions!$C$13 | I19: =I9*Assumptions!$C$13 | J19: =J9*Assumptions!$C$13 | ... N19: =N9*Assumptions!$C$13 | O19: =SUM(C19:N19)
A20: Total people cost | C20: =SUM(C17:C19) | D20: =SUM(D17:D19) | E20: =SUM(E17:E19) | F20: =SUM(F17:F19) | G20: =SUM(G17:G19) | H20: =SUM(H17:H19) | I20: =SUM(I17:I19) | J20: =SUM(J17:J19) | ... N20: =SUM(N17:N19) | O20: =SUM(C20:N20)
A22: Check: total hires in Months 1–6 (must be 25) | C22: =SUM(C9:H9) | D22: =IF(C22=25,"OK","Not 25 – adjust inputs")

Sheet P&L
A1: Profit & loss (monthly)
A2: Interest is shown separately so profit can be read with and without the loan.
A4: USD | C4: 1 | D4: 2 | E4: 3 | F4: 4 | G4: 5 | H4: 6 | I4: 7 | J4: 8 | K4: 9 | L4: 10 | M4: 11 | N4: 12 | O4: 12-month total
A6: Revenue & gross margin
A7: Revenue | C7: =Assumptions!$C$5*(1+Assumptions!$C$6)^(C$4-1) | D7: =Assumptions!$C$5*(1+Assumptions!$C$6)^(D$4-1) | E7: =Assumptions!$C$5*(1+Assumptions!$C$6)^(E$4-1) | F7: =Assumptions!$C$5*(1+Assumptions!$C$6)^(F$4-1) | G7: =Assumptions!$C$5*(1+Assumptions!$C$6)^(G$4-1) | H7: =Assumptions!$C$5*(1+Assumptions!$C$6)^(H$4-1) | I7: =Assumptions!$C$5*(1+Assumptions!$C$6)^(I$4-1) | J7: =Assumptions!$C$5*(1+Assumptions!$C$6)^(J$4-1) | ... N7: =Assumptions!$C$5*(1+Assumptions!$C$6)^(N$4-1) | O7: =SUM(C7:N7)
A8: Gross margin % | C8: =Assumptions!$C$7+(Assumptions!$C$8-Assumptions!$C$7)*(C$4-1)/11 | D8: =Assumptions!$C$7+(Assumptions!$C$8-Assumptions!$C$7)*(D$4-1)/11 | E8: =Assumptions!$C$7+(Assumptions!$C$8-Assumptions!$C$7)*(E$4-1)/11 | F8: =Assumptions!$C$7+(Assumptions!$C$8-Assumptions!$C$7)*(F$4-1)/11 | G8: =Assumptions!$C$7+(Assumptions!$C$8-Assumptions!$C$7)*(G$4-1)/11 | H8: =Assumptions!$C$7+(Assumptions!$C$8-Assumptions!$C$7)*(H$4-1)/11 | I8: =Assumptions!$C$7+(Assumptions!$C$8-Assumptions!$C$7)*(I$4-1)/11 | J8: =Assumptions!$C$7+(Assumptions!$C$8-Assumptions!$C$7)*(J$4-1)/11 | ... N8: =Assumptions!$C$7+(Assumptions!$C$8-Assumptions!$C$7)*(N$4-1)/11 | O8: =O10/O7
A9: Cost of revenue | C9: =-C7*(1-C8) | D9: =-D7*(1-D8) | E9: =-E7*(1-E8) | F9: =-F7*(1-F8) | G9: =-G7*(1-G8) | H9: =-H7*(1-H8) | I9: =-I7*(1-I8) | J9: =-J7*(1-J8) | ... N9: =-N7*(1-N8) | O9: =SUM(C9:N9)
A10: Gross profit | C10: =C7+C9 | D10: =D7+D9 | E10: =E7+E9 | F10: =F7+F9 | G10: =G7+G9 | H10: =H7+H9 | I10: =I7+I9 | J10: =J7+J9 | ... N10: =N7+N9 | O10: =SUM(C10:N10)
A12: Operating expenses
A13: Salaries | C13: =-Headcount!C17 | D13: =-Headcount!D17 | E13: =-Headcount!E17 | F13: =-Headcount!F17 | G13: =-Headcount!G17 | H13: =-Headcount!H17 | I13: =-Headcount!I17 | J13: =-Headcount!J17 | ... N13: =-Headcount!N17 | O13: =SUM(C13:N13)
A14: Benefits | C14: =-Headcount!C18 | D14: =-Headcount!D18 | E14: =-Headcount!E18 | F14: =-Headcount!F18 | G14: =-Headcount!G18 | H14: =-Headcount!H18 | I14: =-Headcount!I18 | J14: =-Headcount!J18 | ... N14: =-Headcount!N18 | O14: =SUM(C14:N14)
A15: Hiring costs | C15: =-Headcount!C19 | D15: =-Headcount!D19 | E15: =-Headcount!E19 | F15: =-Headcount!F19 | G15: =-Headcount!G19 | H15: =-Headcount!H19 | I15: =-Headcount!I19 | J15: =-Headcount!J19 | ... N15: =-Headcount!N19 | O15: =SUM(C15:N15)
A16: Overhead | C16: =-Assumptions!$C$18*(1+Assumptions!$C$19*(C$4-1)/11) | D16: =-Assumptions!$C$18*(1+Assumptions!$C$19*(D$4-1)/11) | E16: =-Assumptions!$C$18*(1+Assumptions!$C$19*(E$4-1)/11) | F16: =-Assumptions!$C$18*(1+Assumptions!$C$19*(F$4-1)/11) | G16: =-Assumptions!$C$18*(1+Assumptions!$C$19*(G$4-1)/11) | H16: =-Assumptions!$C$18*(1+Assumptions!$C$19*(H$4-1)/11) | I16: =-Assumptions!$C$18*(1+Assumptions!$C$19*(I$4-1)/11) | J16: =-Assumptions!$C$18*(1+Assumptions!$C$19*(J$4-1)/11) | ... N16: =-Assumptions!$C$18*(1+Assumptions!$C$19*(N$4-1)/11) | O16: =SUM(C16:N16)
A17: G&A / Legal | C17: =-Assumptions!$C$20 | D17: =-Assumptions!$C$20 | E17: =-Assumptions!$C$20 | F17: =-Assumptions!$C$20 | G17: =-Assumptions!$C$20 | H17: =-Assumptions!$C$20 | I17: =-Assumptions!$C$20 | J17: =-Assumptions!$C$20 | ... N17: =-Assumptions!$C$20 | O17: =SUM(C17:N17)
A18: Total operating expenses | C18: =SUM(C13:C17) | D18: =SUM(D13:D17) | E18: =SUM(E13:E17) | F18: =SUM(F13:F17) | G18: =SUM(G13:G17) | H18: =SUM(H13:H17) | I18: =SUM(I13:I17) | J18: =SUM(J13:J17) | ... N18: =SUM(N13:N17) | O18: =SUM(C18:N18)
A20: Operating profit | C20: =C10+C18 | D20: =D10+D18 | E20: =E10+E18 | F20: =F10+F18 | G20: =G10+G18 | H20: =H10+H18 | I20: =I10+I18 | J20: =J10+J18 | ... N20: =N10+N18 | O20: =SUM(C20:N20)
A21: Operating margin % | C21: =C20/C7 | D21: =D20/D7 | E21: =E20/E7 | F21: =F20/F7 | G21: =G20/G7 | H21: =H20/H7 | I21: =I20/I7 | J21: =J20/J7 | ... O21: =O20/O7
A23: Net profit – WITHOUT loan | C23: =C20 | D23: =D20 | E23: =E20 | F23: =F20 | G23: =G20 | H23: =H20 | I23: =I20 | J23: =J20 | ... N23: =N20 | O23: =SUM(C23:N23)
A24: Loan interest | C24: =-INDEX(Loan!$J$6:$J$29,C$4) | D24: =-INDEX(Loan!$J$6:$J$29,D$4) | E24: =-INDEX(Loan!$J$6:$J$29,E$4) | F24: =-INDEX(Loan!$J$6:$J$29,F$4) | G24: =-INDEX(Loan!$J$6:$J$29,G$4) | H24: =-INDEX(Loan!$J$6:$J$29,H$4) | I24: =-INDEX(Loan!$J$6:$J$29,I$4) | J24: =-INDEX(Loan!$J$6:$J$29,J$4) | ... N24: =-INDEX(Loan!$J$6:$J$29,N$4) | O24: =SUM(C24:N24)
A25: Net profit – WITH loan | C25: =C20+C24 | D25: =D20+D24 | E25: =E20+E24 | F25: =F20+F24 | G25: =G20+G24 | H25: =H20+H24 | I25: =I20+I24 | J25: =J20+J24 | ... N25: =N20+N24 | O25: =SUM(C25:N25)

Sheet Cash Flow
A1: Cash flow statement – indirect method
A2: Starts from net profit and adjusts for non-cash items and working capital. The case brief has none of these, so those lines are zero and cash flow from operations equals net profit.
A4: USD | C4: 1 | D4: 2 | E4: 3 | F4: 4 | G4: 5 | H4: 6 | I4: 7 | J4: 8 | K4: 9 | L4: 10 | M4: 11 | N4: 12 | O4: 12-month total
A6: A. WITHOUT loan
A7: Net profit | C7: ='P&L'!C23 | D7: ='P&L'!D23 | E7: ='P&L'!E23 | F7: ='P&L'!F23 | G7: ='P&L'!G23 | H7: ='P&L'!H23 | I7: ='P&L'!I23 | J7: ='P&L'!J23 | ... N7: ='P&L'!N23 | O7: =SUM(C7:N7)
A8: + Non-cash items (e.g. depreciation) – none in brief | C8: =0 | D8: =0 | E8: =0 | F8: =0 | G8: =0 | H8: =0 | I8: =0 | J8: =0 | ... N8: =0 | O8: =SUM(C8:N8)
A9: ± Change in working capital – none in brief | C9: =0 | D9: =0 | E9: =0 | F9: =0 | G9: =0 | H9: =0 | I9: =0 | J9: =0 | ... N9: =0 | O9: =SUM(C9:N9)
A10: Cash flow from operations | C10: =SUM(C7:C9) | D10: =SUM(D7:D9) | E10: =SUM(E7:E9) | F10: =SUM(F7:F9) | G10: =SUM(G7:G9) | H10: =SUM(H7:H9) | I10: =SUM(I7:I9) | J10: =SUM(J7:J9) | ... N10: =SUM(N7:N9) | O10: =SUM(C10:N10)
A11: Cash flow from investing – none in brief | C11: =0 | D11: =0 | E11: =0 | F11: =0 | G11: =0 | H11: =0 | I11: =0 | J11: =0 | ... N11: =0 | O11: =SUM(C11:N11)
A12: Loan received | C12: =0 | D12: =0 | E12: =0 | F12: =0 | G12: =0 | H12: =0 | I12: =0 | J12: =0 | ... N12: =0 | O12: =SUM(C12:N12)
A13: Loan principal repaid | C13: =0 | D13: =0 | E13: =0 | F13: =0 | G13: =0 | H13: =0 | I13: =0 | J13: =0 | ... N13: =0 | O13: =SUM(C13:N13)
A14: Cash flow from financing | C14: =C12+C13 | D14: =D12+D13 | E14: =E12+E13 | F14: =F12+F13 | G14: =G12+G13 | H14: =H12+H13 | I14: =I12+I13 | J14: =J12+J13 | ... N14: =N12+N13 | O14: =SUM(C14:N14)
A15: Net change in cash | C15: =C10+C11+C14 | D15: =D10+D11+D14 | E15: =E10+E11+E14 | F15: =F10+F11+F14 | G15: =G10+G11+G14 | H15: =H10+H11+H14 | I15: =I10+I11+I14 | J15: =J10+J11+J14 | ... N15: =N10+N11+N14 | O15: =SUM(C15:N15)
A16: Opening cash | C16: =Assumptions!$C$23 | D16: =C17 | E16: =D17 | F16: =E17 | G16: =F17 | H16: =G17 | I16: =H17 | J16: =I17 | K16: =J17 | ... N16: =M17 | O16: =C16
A17: Closing cash | C17: =C16+C15 | D17: =D16+D15 | E17: =E16+E15 | F17: =F16+F15 | G17: =G16+G15 | H17: =H16+H15 | I17: =I16+I15 | J17: =J16+J15 | ... N17: =N16+N15 | O17: =N17
A20: B. WITH €500k loan
A21: Net profit | C21: ='P&L'!C25 | D21: ='P&L'!D25 | E21: ='P&L'!E25 | F21: ='P&L'!F25 | G21: ='P&L'!G25 | H21: ='P&L'!H25 | I21: ='P&L'!I25 | J21: ='P&L'!J25 | ... N21: ='P&L'!N25 | O21: =SUM(C21:N21)
A22: + Non-cash items (e.g. depreciation) – none in brief | C22: =0 | D22: =0 | E22: =0 | F22: =0 | G22: =0 | H22: =0 | I22: =0 | J22: =0 | ... N22: =0 | O22: =SUM(C22:N22)
A23: ± Change in working capital – none in brief | C23: =0 | D23: =0 | E23: =0 | F23: =0 | G23: =0 | H23: =0 | I23: =0 | J23: =0 | ... N23: =0 | O23: =SUM(C23:N23)
A24: Cash flow from operations | C24: =SUM(C21:C23) | D24: =SUM(D21:D23) | E24: =SUM(E21:E23) | F24: =SUM(F21:F23) | G24: =SUM(G21:G23) | H24: =SUM(H21:H23) | I24: =SUM(I21:I23) | J24: =SUM(J21:J23) | ... N24: =SUM(N21:N23) | O24: =SUM(C24:N24)
A25: Cash flow from investing – none in brief | C25: =0 | D25: =0 | E25: =0 | F25: =0 | G25: =0 | H25: =0 | I25: =0 | J25: =0 | ... N25: =0 | O25: =SUM(C25:N25)
A26: Loan received (€500k × FX) | C26: =IF(C$4=1,Assumptions!$C$26*Assumptions!$C$30,0) | D26: =IF(D$4=1,Assumptions!$C$26*Assumptions!$C$30,0) | E26: =IF(E$4=1,Assumptions!$C$26*Assumptions!$C$30,0) | F26: =IF(F$4=1,Assumptions!$C$26*Assumptions!$C$30,0) | G26: =IF(G$4=1,Assumptions!$C$26*Assumptions!$C$30,0) | H26: =IF(H$4=1,Assumptions!$C$26*Assumptions!$C$30,0) | I26: =IF(I$4=1,Assumptions!$C$26*Assumptions!$C$30,0) | J26: =IF(J$4=1,Assumptions!$C$26*Assumptions!$C$30,0) | ... N26: =IF(N$4=1,Assumptions!$C$26*Assumptions!$C$30,0) | O26: =SUM(C26:N26)
A27: Loan principal repaid | C27: =-INDEX(Loan!$I$6:$I$29,C$4) | D27: =-INDEX(Loan!$I$6:$I$29,D$4) | E27: =-INDEX(Loan!$I$6:$I$29,E$4) | F27: =-INDEX(Loan!$I$6:$I$29,F$4) | G27: =-INDEX(Loan!$I$6:$I$29,G$4) | H27: =-INDEX(Loan!$I$6:$I$29,H$4) | I27: =-INDEX(Loan!$I$6:$I$29,I$4) | J27: =-INDEX(Loan!$I$6:$I$29,J$4) | ... N27: =-INDEX(Loan!$I$6:$I$29,N$4) | O27: =SUM(C27:N27)
A28: Cash flow from financing | C28: =C26+C27 | D28: =D26+D27 | E28: =E26+E27 | F28: =F26+F27 | G28: =G26+G27 | H28: =H26+H27 | I28: =I26+I27 | J28: =J26+J27 | ... N28: =N26+N27 | O28: =SUM(C28:N28)
A29: Net change in cash | C29: =C24+C25+C28 | D29: =D24+D25+D28 | E29: =E24+E25+E28 | F29: =F24+F25+F28 | G29: =G24+G25+G28 | H29: =H24+H25+H28 | I29: =I24+I25+I28 | J29: =J24+J25+J28 | ... N29: =N24+N25+N28 | O29: =SUM(C29:N29)
A30: Opening cash | C30: =Assumptions!$C$23 | D30: =C31 | E30: =D31 | F30: =E31 | G30: =F31 | H30: =G31 | I30: =H31 | J30: =I31 | K30: =J31 | ... N30: =M31 | O30: =C30
A31: Closing cash | C31: =C30+C29 | D31: =D30+D29 | E31: =E30+E29 | F31: =F30+F29 | G31: =G30+G29 | H31: =H30+H29 | I31: =I30+I29 | J31: =J30+J29 | ... N31: =N30+N29 | O31: =N31

Sheet Loan
A1: €500k loan – repayment schedule (24 months)
A2: 6% a year = 0.5% a month. Months 1–6: interest only. Months 7–24: equal monthly payments. Converted to USD at the Assumptions FX rate.
A5: Month | B5: Phase | D5: Opening balance (€) | E5: Interest (€) | F5: Principal (€) | G5: Total payment (€) | H5: Closing balance (€) | I5: Principal ($) | J5: Interest ($) | K5: Total payment ($) | L5: Closing balance ($)
A6: 1 | B6: =IF(A6<=Assumptions!$C$29,"Interest only","Repaying") | D6: =Assumptions!$C$26 | E6: =D6*Assumptions!$C$27/12 | F6: =G6-E6 | G6: =IF(A6<=Assumptions!$C$29,E6,-PMT(Assumptions!$C$27/12,Assumptions!$C$28-Assumptions!$C$29,Assumptions!$C$26)) | H6: =D6-F6 | I6: =F6*Assumptions!$C$30 | J6: =E6*Assumptions!$C$30 | K6: =G6*Assumptions!$C$30 | L6: =H6*Assumptions!$C$30
A7: 2 | B7: =IF(A7<=Assumptions!$C$29,"Interest only","Repaying") | D7: =H6 | E7: =D7*Assumptions!$C$27/12 | F7: =G7-E7 | G7: =IF(A7<=Assumptions!$C$29,E7,-PMT(Assumptions!$C$27/12,Assumptions!$C$28-Assumptions!$C$29,Assumptions!$C$26)) | H7: =D7-F7 | I7: =F7*Assumptions!$C$30 | J7: =E7*Assumptions!$C$30 | K7: =G7*Assumptions!$C$30 | L7: =H7*Assumptions!$C$30
A8: 3 | B8: =IF(A8<=Assumptions!$C$29,"Interest only","Repaying") | D8: =H7 | E8: =D8*Assumptions!$C$27/12 | F8: =G8-E8 | G8: =IF(A8<=Assumptions!$C$29,E8,-PMT(Assumptions!$C$27/12,Assumptions!$C$28-Assumptions!$C$29,Assumptions!$C$26)) | H8: =D8-F8 | I8: =F8*Assumptions!$C$30 | J8: =E8*Assumptions!$C$30 | K8: =G8*Assumptions!$C$30 | L8: =H8*Assumptions!$C$30
A9: 4 | B9: =IF(A9<=Assumptions!$C$29,"Interest only","Repaying") | D9: =H8 | E9: =D9*Assumptions!$C$27/12 | F9: =G9-E9 | G9: =IF(A9<=Assumptions!$C$29,E9,-PMT(Assumptions!$C$27/12,Assumptions!$C$28-Assumptions!$C$29,Assumptions!$C$26)) | H9: =D9-F9 | I9: =F9*Assumptions!$C$30 | J9: =E9*Assumptions!$C$30 | K9: =G9*Assumptions!$C$30 | L9: =H9*Assumptions!$C$30
A10: 5 | B10: =IF(A10<=Assumptions!$C$29,"Interest only","Repaying") | D10: =H9 | E10: =D10*Assumptions!$C$27/12 | F10: =G10-E10 | G10: =IF(A10<=Assumptions!$C$29,E10,-PMT(Assumptions!$C$27/12,Assumptions!$C$28-Assumptions!$C$29,Assumptions!$C$26)) | H10: =D10-F10 | I10: =F10*Assumptions!$C$30 | J10: =E10*Assumptions!$C$30 | K10: =G10*Assumptions!$C$30 | L10: =H10*Assumptions!$C$30
A11: 6 | B11: =IF(A11<=Assumptions!$C$29,"Interest only","Repaying") | D11: =H10 | E11: =D11*Assumptions!$C$27/12 | F11: =G11-E11 | G11: =IF(A11<=Assumptions!$C$29,E11,-PMT(Assumptions!$C$27/12,Assumptions!$C$28-Assumptions!$C$29,Assumptions!$C$26)) | H11: =D11-F11 | I11: =F11*Assumptions!$C$30 | J11: =E11*Assumptions!$C$30 | K11: =G11*Assumptions!$C$30 | L11: =H11*Assumptions!$C$30
A12: 7 | B12: =IF(A12<=Assumptions!$C$29,"Interest only","Repaying") | D12: =H11 | E12: =D12*Assumptions!$C$27/12 | F12: =G12-E12 | G12: =IF(A12<=Assumptions!$C$29,E12,-PMT(Assumptions!$C$27/12,Assumptions!$C$28-Assumptions!$C$29,Assumptions!$C$26)) | H12: =D12-F12 | I12: =F12*Assumptions!$C$30 | J12: =E12*Assumptions!$C$30 | K12: =G12*Assumptions!$C$30 | L12: =H12*Assumptions!$C$30
A13: 8 | B13: =IF(A13<=Assumptions!$C$29,"Interest only","Repaying") | D13: =H12 | E13: =D13*Assumptions!$C$27/12 | F13: =G13-E13 | G13: =IF(A13<=Assumptions!$C$29,E13,-PMT(Assumptions!$C$27/12,Assumptions!$C$28-Assumptions!$C$29,Assumptions!$C$26)) | H13: =D13-F13 | I13: =F13*Assumptions!$C$30 | J13: =E13*Assumptions!$C$30 | K13: =G13*Assumptions!$C$30 | L13: =H13*Assumptions!$C$30
A14: 9 | B14: =IF(A14<=Assumptions!$C$29,"Interest only","Repaying") | D14: =H13 | E14: =D14*Assumptions!$C$27/12 | F14: =G14-E14 | G14: =IF(A14<=Assumptions!$C$29,E14,-PMT(Assumptions!$C$27/12,Assumptions!$C$28-Assumptions!$C$29,Assumptions!$C$26)) | H14: =D14-F14 | I14: =F14*Assumptions!$C$30 | J14: =E14*Assumptions!$C$30 | K14: =G14*Assumptions!$C$30 | L14: =H14*Assumptions!$C$30
A15: 10 | B15: =IF(A15<=Assumptions!$C$29,"Interest only","Repaying") | D15: =H14 | E15: =D15*Assumptions!$C$27/12 | F15: =G15-E15 | G15: =IF(A15<=Assumptions!$C$29,E15,-PMT(Assumptions!$C$27/12,Assumptions!$C$28-Assumptions!$C$29,Assumptions!$C$26)) | H15: =D15-F15 | I15: =F15*Assumptions!$C$30 | J15: =E15*Assumptions!$C$30 | K15: =G15*Assumptions!$C$30 | L15: =H15*Assumptions!$C$30
A16: 11 | B16: =IF(A16<=Assumptions!$C$29,"Interest only","Repaying") | D16: =H15 | E16: =D16*Assumptions!$C$27/12 | F16: =G16-E16 | G16: =IF(A16<=Assumptions!$C$29,E16,-PMT(Assumptions!$C$27/12,Assumptions!$C$28-Assumptions!$C$29,Assumptions!$C$26)) | H16: =D16-F16 | I16: =F16*Assumptions!$C$30 | J16: =E16*Assumptions!$C$30 | K16: =G16*Assumptions!$C$30 | L16: =H16*Assumptions!$C$30
A17: 12 | B17: =IF(A17<=Assumptions!$C$29,"Interest only","Repaying") | D17: =H16 | E17: =D17*Assumptions!$C$27/12 | F17: =G17-E17 | G17: =IF(A17<=Assumptions!$C$29,E17,-PMT(Assumptions!$C$27/12,Assumptions!$C$28-Assumptions!$C$29,Assumptions!$C$26)) | H17: =D17-F17 | I17: =F17*Assumptions!$C$30 | J17: =E17*Assumptions!$C$30 | K17: =G17*Assumptions!$C$30 | L17: =H17*Assumptions!$C$30
A18: 13 | B18: =IF(A18<=Assumptions!$C$29,"Interest only","Repaying") | D18: =H17 | E18: =D18*Assumptions!$C$27/12 | F18: =G18-E18 | G18: =IF(A18<=Assumptions!$C$29,E18,-PMT(Assumptions!$C$27/12,Assumptions!$C$28-Assumptions!$C$29,Assumptions!$C$26)) | H18: =D18-F18 | I18: =F18*Assumptions!$C$30 | J18: =E18*Assumptions!$C$30 | K18: =G18*Assumptions!$C$30 | L18: =H18*Assumptions!$C$30
... A29: 24 | B29: =IF(A29<=Assumptions!$C$29,"Interest only","Repaying") | D29: =H28 | E29: =D29*Assumptions!$C$27/12 | F29: =G29-E29 | G29: =IF(A29<=Assumptions!$C$29,E29,-PMT(Assumptions!$C$27/12,Assumptions!$C$28-Assumptions!$C$29,Assumptions!$C$26)) | H29: =D29-F29 | I29: =F29*Assumptions!$C$30 | J29: =E29*Assumptions!$C$30 | K29: =G29*Assumptions!$C$30 | L29: =H29*Assumptions!$C$30
B30: Total, 24 months | E30: =SUM(E6:E29) | F30: =SUM(F6:F29) | G30: =SUM(G6:G29) | I30: =SUM(I6:I29) | J30: =SUM(J6:J29) | K30: =SUM(K6:K29)
B31: Total, Months 1–12 | E31: =SUM(E6:E17) | F31: =SUM(F6:F17) | G31: =SUM(G6:G17) | I31: =SUM(I6:I17) | J31: =SUM(J6:J17) | K31: =SUM(K6:K17)

Sheet Runway
A1: Cash position, burn & runway
A2: Burn = cash going out minus cash coming in. Runway = months until cash runs out at the current burn.
A4: USD | B4: Start | C4: 1 | D4: 2 | E4: 3 | F4: 4 | G4: 5 | H4: 6 | I4: 7 | J4: 8 | K4: 9 | L4: 10 | M4: 11 | N4: 12 | O4: 12-month total
A6: A. WITHOUT loan
A7: Net cash flow in month | C7: ='Cash Flow'!C15 | D7: ='Cash Flow'!D15 | E7: ='Cash Flow'!E15 | F7: ='Cash Flow'!F15 | G7: ='Cash Flow'!G15 | H7: ='Cash Flow'!H15 | I7: ='Cash Flow'!I15 | J7: ='Cash Flow'!J15 | ... N7: ='Cash Flow'!N15 | O7: =SUM(C7:N7)
A8: Monthly burn (positive = losing cash) | C8: =MAX(0,-C7) | D8: =MAX(0,-D7) | E8: =MAX(0,-E7) | F8: =MAX(0,-F7) | G8: =MAX(0,-G7) | H8: =MAX(0,-H7) | I8: =MAX(0,-I7) | J8: =MAX(0,-J7) | ... N8: =MAX(0,-N7) | O8: =SUM(C8:N8)
A9: Cash position (end of month) | B9: =Assumptions!$C$23 | C9: ='Cash Flow'!C17 | D9: ='Cash Flow'!D17 | E9: ='Cash Flow'!E17 | F9: ='Cash Flow'!F17 | G9: ='Cash Flow'!G17 | H9: ='Cash Flow'!H17 | I9: ='Cash Flow'!I17 | J9: ='Cash Flow'!J17 | ... N9: ='Cash Flow'!N17 | O9: =N9
A10: Cumulative cash generated since start | C10: =C9-Assumptions!$C$23 | D10: =D9-Assumptions!$C$23 | E10: =E9-Assumptions!$C$23 | F10: =F9-Assumptions!$C$23 | G10: =G9-Assumptions!$C$23 | H10: =H9-Assumptions!$C$23 | I10: =I9-Assumptions!$C$23 | J10: =J9-Assumptions!$C$23 | ... N10: =N9-Assumptions!$C$23 | O10: =N10
A11: Runway (months of cash at this month's burn) | C11: =IF(C8>0,C9/C8,"No burn") | D11: =IF(D8>0,D9/D8,"No burn") | E11: =IF(E8>0,E9/E8,"No burn") | F11: =IF(F8>0,F9/F8,"No burn") | G11: =IF(G8>0,G9/G8,"No burn") | H11: =IF(H8>0,H9/H8,"No burn") | I11: =IF(I8>0,I9/I8,"No burn") | J11: =IF(J8>0,J9/J8,"No burn") | ... N11: =IF(N8>0,N9/N8,"No burn")
A14: B. WITH €500k loan
A15: Net cash flow in month | C15: ='Cash Flow'!C29 | D15: ='Cash Flow'!D29 | E15: ='Cash Flow'!E29 | F15: ='Cash Flow'!F29 | G15: ='Cash Flow'!G29 | H15: ='Cash Flow'!H29 | I15: ='Cash Flow'!I29 | J15: ='Cash Flow'!J29 | ... N15: ='Cash Flow'!N29 | O15: =SUM(C15:N15)
A16: Monthly burn (positive = losing cash) | C16: =MAX(0,-C15) | D16: =MAX(0,-D15) | E16: =MAX(0,-E15) | F16: =MAX(0,-F15) | G16: =MAX(0,-G15) | H16: =MAX(0,-H15) | I16: =MAX(0,-I15) | J16: =MAX(0,-J15) | ... N16: =MAX(0,-N15) | O16: =SUM(C16:N16)
A17: Cash position (end of month) | B17: =Assumptions!$C$23 | C17: ='Cash Flow'!C31 | D17: ='Cash Flow'!D31 | E17: ='Cash Flow'!E31 | F17: ='Cash Flow'!F31 | G17: ='Cash Flow'!G31 | H17: ='Cash Flow'!H31 | I17: ='Cash Flow'!I31 | J17: ='Cash Flow'!J31 | ... N17: ='Cash Flow'!N31 | O17: =N17
A18: Cumulative cash generated since start | C18: =C17-Assumptions!$C$23 | D18: =D17-Assumptions!$C$23 | E18: =E17-Assumptions!$C$23 | F18: =F17-Assumptions!$C$23 | G18: =G17-Assumptions!$C$23 | H18: =H17-Assumptions!$C$23 | I18: =I17-Assumptions!$C$23 | J18: =J17-Assumptions!$C$23 | ... N18: =N17-Assumptions!$C$23 | O18: =N18
A19: Runway (months of cash at this month's burn) | C19: =IF(C16>0,C17/C16,"No burn") | D19: =IF(D16>0,D17/D16,"No burn") | E19: =IF(E16>0,E17/E16,"No burn") | F19: =IF(F16>0,F17/F16,"No burn") | G19: =IF(G16>0,G17/G16,"No burn") | H19: =IF(H16>0,H17/H16,"No burn") | I19: =IF(I16>0,I17/I16,"No burn") | J19: =IF(J16>0,J17/J16,"No burn") | ... N19: =IF(N16>0,N17/N16,"No burn")
A23: Comparison | C23: Without loan | D23: With loan | E23: Difference
A24: Cash at end of Month 12 | C24: =N9 | D24: =N17 | E24: =D24-C24
A25: Lowest cash position in the 12 months | C25: =MIN($C$9:$N$9) | D25: =MIN($C$17:$N$17) | E25: =D25-C25
A26: Months with cash burn (of 12) | C26: =COUNTIF($C$8:$N$8,">0") | D26: =COUNTIF($C$16:$N$16,">0") | E26: =D26-C26
A27: Loan still owed at end of Month 12 | C27: =0 | D27: =Loan!L17 | E27: =D27-C27
A28: Cash minus loan owed, Month 12 | C28: =C24-C27 | D28: =D24-D27 | E28: =D28-C28
A29: Interest paid in the 12 months | C29: =0 | D29: =Loan!J31 | E29: =D29-C29
A30: Runway | C30: =IF(C26=0,"No burn",MIN($C$11:$N$11)) | D30: =IF(D26=0,"No burn",MIN($C$19:$N$19))
